_libheif_cffi.cpython-310-darwin.so
_libheif_cffi.cpython-311-darwin.so
pyheif/__init__.py
pyheif/constants.py
pyheif/error.py
pyheif/reader.py
pyheif/writer.py
pyheif/data/version.txt
pyheif_iplweb-0.7.1.dev1176.dist-info/LICENSE
pyheif_iplweb-0.7.1.dev1176.dist-info/METADATA
pyheif_iplweb-0.7.1.dev1176.dist-info/WHEEL
pyheif_iplweb-0.7.1.dev1176.dist-info/top_level.txt
pyheif_iplweb-0.7.1.dev1176.dist-info/RECORD
