Metadata-Version: 2.1
Name: pyheif-iplweb
Version: 0.7.1.dev1176
Summary: Python 3.6+ interface to libheif library
Home-page: https://github.com/carsales/pyheif
Author: Anthony Paes
Author-email: ant32bit-carsales@users.noreply.github.com
Keywords: heif heic
Classifier: Programming Language :: Python :: 3
Classifier: License :: OSI Approved :: Apache Software License
Classifier: Operating System :: MacOS :: MacOS X
Classifier: Operating System :: POSIX :: Linux
Requires-Python: ~=3.10
License-File: LICENSE
Requires-Dist: cffi >=1.0.0
